pgargs/__init__.py
pgargs/py.typed
pgargs-0.1.0.dist-info/METADATA
pgargs-0.1.0.dist-info/WHEEL
pgargs-0.1.0.dist-info/RECORD
