Metadata-Version: 2.4
Name: pgargs
Version: 0.1.0
Summary: Named arguments for asyncpg
Project-URL: homepage, https://github.com/raymondbutcher/pgargs
Project-URL: repository, https://github.com/raymondbutcher/pgargs.git
Author: Raymond Butcher
License: MIT License
Keywords: asyncpg
Requires-Python: >=3.9
